LICENSE
MANIFEST.in
ReadMe.md
TODO.md
requirements.txt
setup.py
docs/test.txt
pic/TAIScoreLogo.png
tests/test_merge.ipynb
tscore/__init__.py
tscore/base.py
tscore/deploy.py
tscore/eda.py
tscore/features.py
tscore/interpreter.py
tscore/metrics.py
tscore/model_selection.py
tscore/monitor.py
tscore/pipeline.py
tscore/plot.py
tscore/preprocessing.py
tscore/report.py
tscore/risk_rules.py
tscore/version.py
tscore.egg-info/PKG-INFO
tscore.egg-info/SOURCES.txt
tscore.egg-info/dependency_links.txt
tscore.egg-info/entry_points.txt
tscore.egg-info/requires.txt
tscore.egg-info/top_level.txt
tscore/ml/__init__.py
tscore/score_card/__init__.py
tscore/score_card/merge.py